[
  { "name": "Dallas", "airports": ["DFW", "DAL"] },
  { "name": "Houston", "airports": ["IAH", "HOU", "EFD"] },
  { "name": "New York", "airports": ["JFK", "LGA", "EWR", "HPN", "ISP"] },
  { "name": "Washington DC", "airports": ["IAD", "DCA", "BWI"] },
  { "name": "Chicago", "airports": ["ORD", "MDW"] },
  { "name": "Bay Area", "airports": ["SFO", "OAK", "SJC"] },
  { "name": "Los Angeles", "airports": ["LAX", "BUR", "SNA", "ONT", "LGB"] },
  { "name": "South Florida", "airports": ["MIA", "FLL", "PBI"] },
  { "name": "London", "airports": ["LHR", "LGW", "STN", "LTN", "LCY", "SEN"] },
  { "name": "Boston", "airports": ["BOS", "PVD", "MHT"] },
  { "name": "Rio Grande Valley", "airports": ["HRL", "BRO", "MFE"] },
  { "name": "Tokyo", "airports": ["HND", "NRT"] },
  { "name": "Paris", "airports": ["CDG", "ORY", "BVA"] },
  { "name": "Seoul", "airports": ["ICN", "GMP"] },
  { "name": "Milan", "airports": ["MXP", "LIN", "BGY"] },
  { "name": "Sao Paulo", "airports": ["GRU", "CGH", "VCP"] },
  { "name": "Moscow", "airports": ["SVO", "DME", "VKO"] },
  { "name": "Rome", "airports": ["FCO", "CIA"] },
  { "name": "Bangkok", "airports": ["BKK", "DMK"] },
  { "name": "Istanbul", "airports": ["IST", "SAW"] },
  { "name": "Buenos Aires", "airports": ["EZE", "AEP"] },
  { "name": "Stockholm", "airports": ["ARN", "BMA", "NYO"] },
  { "name": "Osaka", "airports": ["KIX", "ITM"] },
  { "name": "Shanghai", "airports": ["PVG", "SHA"] },
  { "name": "Berlin", "airports": ["BER"] },
  { "name": "Toronto", "airports": ["YYZ", "YTZ"] },
  { "name": "Montreal", "airports": ["YUL", "YMX"] }
]
